topsis/topsis.py
Topsis_ParthGarg_101903558-1.0.0.dist-info/LICENSE
Topsis_ParthGarg_101903558-1.0.0.dist-info/METADATA
Topsis_ParthGarg_101903558-1.0.0.dist-info/WHEEL
Topsis_ParthGarg_101903558-1.0.0.dist-info/entry_points.txt
Topsis_ParthGarg_101903558-1.0.0.dist-info/top_level.txt
Topsis_ParthGarg_101903558-1.0.0.dist-info/RECORD
