Metadata-Version: 2.1
Name: Topsis-ParthGarg-101903558
Version: 1.0.0
Summary: It gives a csv file.
Home-page: UNKNOWN
Author: Parth Garg
Author-email: parthgarg2013@gmail.com
License: MIT
Platform: UNKNOWN
Classifier: License :: OSI Approved :: MIT License
Classifier: Programming Language :: Python :: 3.6
Classifier: Programming Language :: Python :: 3.7
Classifier: Programming Language :: Python :: 3.8
Classifier: Programming Language :: Python :: 3.8
Classifier: Programming Language :: Python :: 3.9
Requires-Dist: pandas
Requires-Dist: numpy
